{
  "indexes": [
    {
      "collectionGroup": "meals",
      "queryScope": "COLLECTION",
      "fields": [
        {
          "fieldPath": "timestamp",
          "order": "DESCENDING"
        },
        {
          "fieldPath": "status",
          "order": "ASCENDING"
        }
      ]
    },
    {
      "collectionGroup": "users",
      "queryScope": "COLLECTION",
      "fields": [
        {
          "fieldPath": "lastPatternAnalysis",
          "order": "ASCENDING"
        }
      ]
    },
    {
      "collectionGroup": "patterns",
      "queryScope": "COLLECTION",
      "fields": [
        {
          "fieldPath": "createdAt",
          "order": "DESCENDING"
        },
        {
          "fieldPath": "type",
          "order": "ASCENDING"
        }
      ]
    },
    {
      "collectionGroup": "insights",
      "queryScope": "COLLECTION",
      "fields": [
        {
          "fieldPath": "createdAt",
          "order": "DESCENDING"
        },
        {
          "fieldPath": "priority",
          "order": "DESCENDING"
        }
      ]
    }
  ],
  "fieldOverrides": []
}